<?xml version="1.0" encoding="UTF-8"?>  
<!-- Copyright FUJITSU LIMITED 2018 -->
<!DOCTYPE task PUBLIC "-//OASIS//DTD DITA Task//EN"
                      "task.dtd" >
<task id="task634" xml:lang="de-de">
  <title>Neues Passwort festlegen</title>
  <taskbody>
    <context>
      <p>Sie haben f체r Ihren Benutzernamen ein neues Passwort festgelegt und werden zur Seite <uicontrol>Anmelden</uicontrol> weitergeleitet. Verwenden Sie ab sofort das neue Passwort, um sich anzumelden. </p>
      <p>Per Email erhalten Sie zus채tzlich eine Best채tigung, dass Sie Ihr Passwort erfolgreich ge채ndert haben.</p>
    </context>
  </taskbody>
</task>
